mochio/__init__.py
mochio/__main__.py
mochio-1.0.0.dist-info/METADATA
mochio-1.0.0.dist-info/WHEEL
mochio-1.0.0.dist-info/top_level.txt
mochio-1.0.0.dist-info/RECORD
