Metadata-Version: 2.1
Name: mochio
Version: 1.0.0
Summary: A general-purpose library
Home-page: UNKNOWN
Author: Mohammed Aljaroudi
Author-email: UNKNOWN
License: MIT
Platform: UNKNOWN
